dj_multihash/__init__.py
dj_multihash/dj_multihash.py
dj_multihash-1.0.dist-info/LICENSE
dj_multihash-1.0.dist-info/METADATA
dj_multihash-1.0.dist-info/WHEEL
dj_multihash-1.0.dist-info/top_level.txt
dj_multihash-1.0.dist-info/RECORD
