Metadata-Version: 2.1
Name: dj-multihash
Version: 1.0
Summary: DJ-MultiHash by DJOPRO_YT
Home-page: 
Author: DJSTUDIO
Classifier: Programming Language :: Python :: 3
Classifier: License :: OSI Approved :: MIT License
Classifier: Operating System :: OS Independent
Requires-Python: >=3.6
License-File: LICENSE
